arithmetic/__init__.py
arithmetic/arithmetic.py
arithmetic_yjiang-0.0.1.dist-info/METADATA
arithmetic_yjiang-0.0.1.dist-info/WHEEL
arithmetic_yjiang-0.0.1.dist-info/top_level.txt
arithmetic_yjiang-0.0.1.dist-info/RECORD
